kfai_sql_chemistry/__init__.py
kfai_sql_chemistry/_version.py
kfai_sql_chemistry/aws/__init__.py
kfai_sql_chemistry/aws/aws_db_config.py
kfai_sql_chemistry/aws/secrets.py
kfai_sql_chemistry/db/__init__.py
kfai_sql_chemistry/db/database_config.py
kfai_sql_chemistry/db/engines.py
kfai_sql_chemistry/db/main.py
kfai_sql_chemistry/db/retry_query.py
kfai_sql_chemistry/db/session.py
kfai_sql_chemistry/utils/__init__.py
kfai_sql_chemistry/utils/setup_for_testing.py
kungfuai_sql_chemistry-0.0.12.dist-info/LICENSE
kungfuai_sql_chemistry-0.0.12.dist-info/METADATA
kungfuai_sql_chemistry-0.0.12.dist-info/WHEEL
kungfuai_sql_chemistry-0.0.12.dist-info/top_level.txt
kungfuai_sql_chemistry-0.0.12.dist-info/RECORD
