Metadata-Version: 2.1
Name: kungfuai-sql-chemistry
Version: 0.0.12
Summary: Environment handling to simplify development environments
Home-page: https://github.com/kungfuai/sql-chemistry
Author: Endurance Idehen
Author-email: endurance.idehen@kungfu.ai
License: MIT
Platform: UNKNOWN
Classifier: License :: OSI Approved :: MIT License
Classifier: Programming Language :: Python :: 3
Classifier: Programming Language :: Python :: 3.8
Requires-Dist: dataclasses-json
Requires-Dist: SQLAlchemy
Requires-Dist: SQLAlchemy-Utils
Requires-Dist: psycopg2-binary
Requires-Dist: boto3
